{
  "type": "File",
  "start": 0,
  "end": 69,
  "loc": {
    "start": {
      "line": 1,
      "column": 0
    },
    "end": {
      "line": 2,
      "column": 0
    }
  },
  "program": {
    "type": "Program",
    "start": 0,
    "end": 69,
    "loc": {
      "start": {
        "line": 1,
        "column": 0
      },
      "end": {
        "line": 2,
        "column": 0
      }
    },
    "sourceType": "module",
    "body": [
      {
        "type": "ExportNamedDeclaration",
        "start": 0,
        "end": 68,
        "loc": {
          "start": {
            "line": 1,
            "column": 0
          },
          "end": {
            "line": 1,
            "column": 68
          }
        },
        "declaration": null,
        "specifiers": [
          {
            "type": "ExportSpecifier",
            "start": 8,
            "end": 36,
            "loc": {
              "start": {
                "line": 1,
                "column": 8
              },
              "end": {
                "line": 1,
                "column": 36
              }
            },
            "local": {
              "type": "Identifier",
              "start": 8,
              "end": 15,
              "loc": {
                "start": {
                  "line": 1,
                  "column": 8
                },
                "end": {
                  "line": 1,
                  "column": 15
                },
                "identifierName": "default"
              },
              "name": "default"
            },
            "exported": {
              "type": "Identifier",
              "start": 19,
              "end": 36,
              "loc": {
                "start": {
                  "line": 1,
                  "column": 19
                },
                "end": {
                  "line": 1,
                  "column": 36
                },
                "identifierName": "multicombinations"
              },
              "name": "multicombinations"
            }
          }
        ],
        "source": {
          "type": "StringLiteral",
          "start": 43,
          "end": 67,
          "loc": {
            "start": {
              "line": 1,
              "column": 43
            },
            "end": {
              "line": 1,
              "column": 67
            }
          },
          "extra": {
            "rawValue": "./multicombinations.js",
            "raw": "'./multicombinations.js'"
          },
          "value": "./multicombinations.js"
        }
      }
    ],
    "directives": []
  },
  "comments": [],
  "tokens": [
    {
      "type": {
        "label": "export",
        "keyword": "export",
        "beforeExpr": false,
        "startsExpr": false,
        "rightAssociative": false,
        "isLoop": false,
        "isAssign": false,
        "prefix": false,
        "postfix": false,
        "binop": null,
        "updateContext": null
      },
      "value": "export",
      "start": 0,
      "end": 6,
      "loc": {
        "start": {
          "line": 1,
          "column": 0
        },
        "end": {
          "line": 1,
          "column": 6
        }
      }
    },
    {
      "type": {
        "label": "{",
        "beforeExpr": true,
        "startsExpr": true,
        "rightAssociative": false,
        "isLoop": false,
        "isAssign": false,
        "prefix": false,
        "postfix": false,
        "binop": null
      },
      "start": 7,
      "end": 8,
      "loc": {
        "start": {
          "line": 1,
          "column": 7
        },
        "end": {
          "line": 1,
          "column": 8
        }
      }
    },
    {
      "type": {
        "label": "default",
        "keyword": "default",
        "beforeExpr": true,
        "startsExpr": false,
        "rightAssociative": false,
        "isLoop": false,
        "isAssign": false,
        "prefix": false,
        "postfix": false,
        "binop": null,
        "updateContext": null
      },
      "value": "default",
      "start": 8,
      "end": 15,
      "loc": {
        "start": {
          "line": 1,
          "column": 8
        },
        "end": {
          "line": 1,
          "column": 15
        }
      }
    },
    {
      "type": {
        "label": "name",
        "beforeExpr": false,
        "startsExpr": true,
        "rightAssociative": false,
        "isLoop": false,
        "isAssign": false,
        "prefix": false,
        "postfix": false,
        "binop": null
      },
      "value": "as",
      "start": 16,
      "end": 18,
      "loc": {
        "start": {
          "line": 1,
          "column": 16
        },
        "end": {
          "line": 1,
          "column": 18
        }
      }
    },
    {
      "type": {
        "label": "name",
        "beforeExpr": false,
        "startsExpr": true,
        "rightAssociative": false,
        "isLoop": false,
        "isAssign": false,
        "prefix": false,
        "postfix": false,
        "binop": null
      },
      "value": "multicombinations",
      "start": 19,
      "end": 36,
      "loc": {
        "start": {
          "line": 1,
          "column": 19
        },
        "end": {
          "line": 1,
          "column": 36
        }
      }
    },
    {
      "type": {
        "label": "}",
        "beforeExpr": false,
        "startsExpr": false,
        "rightAssociative": false,
        "isLoop": false,
        "isAssign": false,
        "prefix": false,
        "postfix": false,
        "binop": null
      },
      "start": 36,
      "end": 37,
      "loc": {
        "start": {
          "line": 1,
          "column": 36
        },
        "end": {
          "line": 1,
          "column": 37
        }
      }
    },
    {
      "type": {
        "label": "name",
        "beforeExpr": false,
        "startsExpr": true,
        "rightAssociative": false,
        "isLoop": false,
        "isAssign": false,
        "prefix": false,
        "postfix": false,
        "binop": null
      },
      "value": "from",
      "start": 38,
      "end": 42,
      "loc": {
        "start": {
          "line": 1,
          "column": 38
        },
        "end": {
          "line": 1,
          "column": 42
        }
      }
    },
    {
      "type": {
        "label": "string",
        "beforeExpr": false,
        "startsExpr": true,
        "rightAssociative": false,
        "isLoop": false,
        "isAssign": false,
        "prefix": false,
        "postfix": false,
        "binop": null,
        "updateContext": null
      },
      "value": "./multicombinations.js",
      "start": 43,
      "end": 67,
      "loc": {
        "start": {
          "line": 1,
          "column": 43
        },
        "end": {
          "line": 1,
          "column": 67
        }
      }
    },
    {
      "type": {
        "label": ";",
        "beforeExpr": true,
        "startsExpr": false,
        "rightAssociative": false,
        "isLoop": false,
        "isAssign": false,
        "prefix": false,
        "postfix": false,
        "binop": null,
        "updateContext": null
      },
      "start": 67,
      "end": 68,
      "loc": {
        "start": {
          "line": 1,
          "column": 67
        },
        "end": {
          "line": 1,
          "column": 68
        }
      }
    },
    {
      "type": {
        "label": "eof",
        "beforeExpr": false,
        "startsExpr": false,
        "rightAssociative": false,
        "isLoop": false,
        "isAssign": false,
        "prefix": false,
        "postfix": false,
        "binop": null,
        "updateContext": null
      },
      "start": 69,
      "end": 69,
      "loc": {
        "start": {
          "line": 2,
          "column": 0
        },
        "end": {
          "line": 2,
          "column": 0
        }
      }
    }
  ]
}